hypothesize/__init__.py
hypothesize/utilities.py
hypothesize/compare_groups_with_single_factor/__init__.py
hypothesize/compare_groups_with_single_factor/_compare_groups_with_single_factor.py
hypothesize/compare_groups_with_two_factors/__init__.py
hypothesize/compare_groups_with_two_factors/_compare_groups_with_two_factors.py
hypothesize/measuring_associations/__init__.py
hypothesize/measuring_associations/_measuring_associations.py
hypothesize/tests/__init__.py
hypothesize/tests/build_test_data.py
hypothesize/tests/test_funcs.py
hypothesize-1.2.3.dist-info/licenses/LICENSE
hypothesize-1.2.3.dist-info/METADATA
hypothesize-1.2.3.dist-info/WHEEL
hypothesize-1.2.3.dist-info/top_level.txt
hypothesize-1.2.3.dist-info/RECORD
