Metadata-Version: 2.4
Name: hypothesize
Version: 1.2.3
Summary: A Python package for comparing groups and measuring associations using robust statistics.
Home-page: https://github.com/Alcampopiano/hypothesize
Author: Allan Campopiano
Author-email: campopianoa@hcdsb.org
License: BSD 3-clause
Classifier: Development Status :: 5 - Production/Stable
Classifier: Environment :: Console
Classifier: Intended Audience :: Science/Research
Classifier: License :: OSI Approved :: BSD License
Classifier: Natural Language :: English
Classifier: Programming Language :: Python :: 3.6
Classifier: Programming Language :: Python :: 3.7
Classifier: Programming Language :: Python :: 3.8
Classifier: Programming Language :: Python :: 3.10
Requires-Python: >=3.6
License-File: LICENSE
Requires-Dist: scipy>=1.10.0
Requires-Dist: pandas>=1.4.2
Requires-Dist: numpy>=1.22.0
Requires-Dist: more-itertools>=8.12.0
Dynamic: author
Dynamic: author-email
Dynamic: classifier
Dynamic: description
Dynamic: description-content-type
Dynamic: home-page
Dynamic: license
Dynamic: license-file
Dynamic: requires-dist
Dynamic: requires-python
Dynamic: summary
